README.md
setup.cfg
setup.py
python_version/__init__.py
python_version.egg-info/PKG-INFO
python_version.egg-info/SOURCES.txt
python_version.egg-info/dependency_links.txt
python_version.egg-info/top_level.txt