Metadata-Version: 1.1
Name: python-version
Version: 0.0.2
Summary: Provides a simple utility for checking the python version.
Home-page: https://gitlab.com/halfak/python_version
Author: Aaron Halfaker
Author-email: aaron.halfaker@gmail.com
License: MIT License
Platform: UNKNOWN
Classifier: Programming Language :: Python
